Classfile /home/void/tryhackme/JVM_Reverse_Engineering/crack_a_password_protected_application/PasswordProtectedApplication.class
  Last modified 23-Feb-2022; size 735 bytes
  MD5 checksum 5ad7ff92fa2461a0ae59cfcd6c85d8d7
  Compiled from "PasswordProtectedApplication.java"
public class PasswordProtectedApplication
  minor version: 0
  major version: 52
  flags: (0x0021) ACC_PUBLIC, ACC_SUPER
  this_class: #9                          // PasswordProtectedApplication
  super_class: #10                        // java/lang/Object
  interfaces: 0, fields: 0, methods: 2, attributes: 1
Constant pool:
   #1 = Methodref          #10.#21        // java/lang/Object."<init>":()V
   #2 = String             #22            // yxvF2ho95ANJVCX
   #3 = Methodref          #23.#24        // java/lang/String.equals:(Ljava/lang/Object;)Z
   #4 = Fieldref           #25.#26        // java/lang/System.out:Ljava/io/PrintStream;
   #5 = String             #27            // You guessed the correct password
   #6 = Methodref          #28.#29        // java/io/PrintStream.println:(Ljava/lang/String;)V
   #7 = String             #30            // You guessed the wrong password
   #8 = String             #31            // Please supply a password
   #9 = Class              #32            // PasswordProtectedApplication
  #10 = Class              #33            // java/lang/Object
  #11 = Utf8               <init>
  #12 = Utf8               ()V
  #13 = Utf8               Code
  #14 = Utf8               LineNumberTable
  #15 = Utf8               main
  #16 = Utf8               ([Ljava/lang/String;)V
  #17 = Utf8               StackMapTable
  #18 = Class              #34            // java/lang/String
  #19 = Utf8               SourceFile
  #20 = Utf8               PasswordProtectedApplication.java
  #21 = NameAndType        #11:#12        // "<init>":()V
  #22 = Utf8               yxvF2ho95ANJVCX
  #23 = Class              #34            // java/lang/String
  #24 = NameAndType        #35:#36        // equals:(Ljava/lang/Object;)Z
  #25 = Class              #37            // java/lang/System
  #26 = NameAndType        #38:#39        // out:Ljava/io/PrintStream;
  #27 = Utf8               You guessed the correct password
  #28 = Class              #40            // java/io/PrintStream
  #29 = NameAndType        #41:#42        // println:(Ljava/lang/String;)V
  #30 = Utf8               You guessed the wrong password
  #31 = Utf8               Please supply a password
  #32 = Utf8               PasswordProtectedApplication
  #33 = Utf8               java/lang/Object
  #34 = Utf8               java/lang/String
  #35 = Utf8               equals
  #36 = Utf8               (Ljava/lang/Object;)Z
  #37 = Utf8               java/lang/System
  #38 = Utf8               out
  #39 = Utf8               Ljava/io/PrintStream;
  #40 = Utf8               java/io/PrintStream
  #41 = Utf8               println
  #42 = Utf8               (Ljava/lang/String;)V
{
  public PasswordProtectedApplication();
    descriptor: ()V
    flags: (0x0001) ACC_PUBLIC
    Code:
      stack=1, locals=1, args_size=1
         0: aload_0
         1: invokespecial #1                  // Method java/lang/Object."<init>":()V
         4: return
      LineNumberTable:
        line 1: 0

  public static void main(java.lang.String[]);
    descriptor: ([Ljava/lang/String;)V
    flags: (0x0009) ACC_PUBLIC, ACC_STATIC
    Code:
      stack=2, locals=2, args_size=1
         0: aload_0
         1: arraylength
         2: iconst_1
         3: if_icmplt     37
         6: aload_0
         7: iconst_0
         8: aaload
         9: astore_1
        10: aload_1
        11: ldc           #2                  // String yxvF2ho95ANJVCX
        13: invokevirtual #3                  // Method java/lang/String.equals:(Ljava/lang/Object;)Z
        16: ifeq          28
        19: getstatic     #4                  // Field java/lang/System.out:Ljava/io/PrintStream;
        22: ldc           #5                  // String You guessed the correct password
        24: invokevirtual #6                  // Method java/io/PrintStream.println:(Ljava/lang/String;)V
        27: return
        28: getstatic     #4                  // Field java/lang/System.out:Ljava/io/PrintStream;
        31: ldc           #7                  // String You guessed the wrong password
        33: invokevirtual #6                  // Method java/io/PrintStream.println:(Ljava/lang/String;)V
        36: return
        37: getstatic     #4                  // Field java/lang/System.out:Ljava/io/PrintStream;
        40: ldc           #8                  // String Please supply a password
        42: invokevirtual #6                  // Method java/io/PrintStream.println:(Ljava/lang/String;)V
        45: return
      LineNumberTable:
        line 3: 0
        line 4: 6
        line 6: 10
        line 7: 19
        line 8: 27
        line 10: 28
        line 11: 36
        line 14: 37
        line 15: 45
      StackMapTable: number_of_entries = 2
        frame_type = 252 /* append */
          offset_delta = 28
          locals = [ class java/lang/String ]
        frame_type = 250 /* chop */
          offset_delta = 8
}
SourceFile: "PasswordProtectedApplication.java"
